django_versioning-0.1.7.dist-info/licenses/LICENSE
version_control/__init__.py
version_control/admin.py
version_control/apps.py
version_control/managers.py
version_control/models.py
version_control/signals.py
version_control/migrations/0001_initial.py
version_control/migrations/__init__.py
django_versioning-0.1.7.dist-info/METADATA
django_versioning-0.1.7.dist-info/WHEEL
django_versioning-0.1.7.dist-info/top_level.txt
django_versioning-0.1.7.dist-info/RECORD
