Metadata-Version: 2.4
Name: django-versioning
Version: 0.1.7
Summary: django-versioning adds version history, diffs, rollbacks, and audit trails to Django models—fully integrated with the admin.
Home-page: https://github.com/deepak7448/django-versioning
Author: Deepak Prajapati
Author-email: prajapatideepak244@gmail.com
License: MIT
Project-URL: Source, https://github.com/deepak7448/django-versioning
Project-URL: Tracker, https://github.com/deepak7448/django-versioning/issues
Classifier: Programming Language :: Python :: 3
Classifier: Programming Language :: Python :: 3.8
Classifier: Programming Language :: Python :: 3.9
Classifier: Programming Language :: Python :: 3.10
Classifier: Programming Language :: Python :: 3.11
Classifier: Programming Language :: Python :: 3.12
Classifier: Framework :: Django
Classifier: Framework :: Django :: 3.2
Classifier: Framework :: Django :: 4.2
Classifier: Framework :: Django :: 5.0
Classifier: License :: OSI Approved :: MIT License
Requires-Python: >=3.8
License-File: LICENSE
Requires-Dist: Django>=3.2
Requires-Dist: django-crequest>=2018.5.11
Requires-Dist: django-admin-rangefilter>=0.11.0
Provides-Extra: dev
Requires-Dist: setuptools-scm; extra == "dev"
Dynamic: description
Dynamic: license-file
